mistralai_azure/__init__.py
mistralai_azure/_hooks/__init__.py
mistralai_azure/_hooks/custom_user_agent.py
mistralai_azure/_hooks/registration.py
mistralai_azure/_hooks/sdkhooks.py
mistralai_azure/_hooks/types.py
mistralai_azure/_version.py
mistralai_azure/basesdk.py
mistralai_azure/chat.py
mistralai_azure/httpclient.py
mistralai_azure/models/__init__.py
mistralai_azure/models/assistantmessage.py
mistralai_azure/models/chatcompletionchoice.py
mistralai_azure/models/chatcompletionrequest.py
mistralai_azure/models/chatcompletionresponse.py
mistralai_azure/models/chatcompletionstreamrequest.py
mistralai_azure/models/completionchunk.py
mistralai_azure/models/completionevent.py
mistralai_azure/models/completionresponsestreamchoice.py
mistralai_azure/models/contentchunk.py
mistralai_azure/models/deltamessage.py
mistralai_azure/models/function.py
mistralai_azure/models/functioncall.py
mistralai_azure/models/functionname.py
mistralai_azure/models/httpvalidationerror.py
mistralai_azure/models/imageurl.py
mistralai_azure/models/imageurlchunk.py
mistralai_azure/models/jsonschema.py
mistralai_azure/models/prediction.py
mistralai_azure/models/referencechunk.py
mistralai_azure/models/responseformat.py
mistralai_azure/models/responseformats.py
mistralai_azure/models/sdkerror.py
mistralai_azure/models/security.py
mistralai_azure/models/systemmessage.py
mistralai_azure/models/textchunk.py
mistralai_azure/models/tool.py
mistralai_azure/models/toolcall.py
mistralai_azure/models/toolchoice.py
mistralai_azure/models/toolchoiceenum.py
mistralai_azure/models/toolmessage.py
mistralai_azure/models/tooltypes.py
mistralai_azure/models/usageinfo.py
mistralai_azure/models/usermessage.py
mistralai_azure/models/validationerror.py
mistralai_azure/py.typed
mistralai_azure/sdk.py
mistralai_azure/sdkconfiguration.py
mistralai_azure/types/__init__.py
mistralai_azure/types/basemodel.py
mistralai_azure/utils/__init__.py
mistralai_azure/utils/annotations.py
mistralai_azure/utils/enums.py
mistralai-1.8.0.dist-info/LICENSE
mistralai-1.8.0.dist-info/METADATA
mistralai-1.8.0.dist-info/WHEEL
mistralai-1.8.0.dist-info/RECORD
